ekgen/__init__.py
ekgen/__main__.py
ekgen/eam.py
ekgen/main.py
ekgen/mpasocn.py
ekgen/utils.py
ekgen-0.2.1.dist-info/LICENSE
ekgen-0.2.1.dist-info/METADATA
ekgen-0.2.1.dist-info/WHEEL
ekgen-0.2.1.dist-info/entry_points.txt
ekgen-0.2.1.dist-info/top_level.txt
ekgen-0.2.1.dist-info/RECORD
