Metadata-Version: 2.1
Name: ekgen
Version: 0.2.1
Summary: E3SM Fortran Kernel Generator
Home-page: UNKNOWN
Author: Youngsung Kim
Author-email: youngsung.kim.act2@gmail.com
License: UNKNOWN
Project-URL: Bug Reports, https://github.com/grnydawn/ekgen/issues
Project-URL: Source, https://github.com/grnydawn/ekgen
Keywords: microapp fortlab ekgen
Platform: UNKNOWN
Classifier: Development Status :: 3 - Alpha
Classifier: Intended Audience :: Science/Research
Classifier: Topic :: Scientific/Engineering
Classifier: License :: OSI Approved :: MIT License
Classifier: Programming Language :: Python :: 3
Classifier: Programming Language :: Python :: 3.5
Classifier: Programming Language :: Python :: 3.6
Classifier: Programming Language :: Python :: 3.7
Classifier: Programming Language :: Python :: 3.8
Requires-Dist: fortlab (>=0.1.7)
